pyramid_frontend
