Metadata-Version: 1.1
Name: pyramid-frontend
Version: 0.6.2
Summary: Themes, image filtering, and frontend asset handling.
Home-page: http://github.com/cartlogic/pyramid_frontend
Author: Scott Torborg
Author-email: scott@cartlogic.com
License: MIT
Keywords: pyramid themes frontend assets
Platform: UNKNOWN
Classifier: Development Status :: 3 - Alpha
Classifier: License :: OSI Approved :: MIT License
Classifier: Programming Language :: Python :: 2
Classifier: Programming Language :: Python :: 2.7
Classifier: Programming Language :: Python :: 3
Classifier: Programming Language :: Python :: 3.3
Classifier: Programming Language :: Python :: 3.4
Classifier: Programming Language :: Python :: 3.5
Classifier: Framework :: Pyramid
Classifier: Intended Audience :: Developers
Classifier: Topic :: Internet :: WWW/HTTP
Classifier: Topic :: Multimedia :: Graphics
